setty/__init__.py
setty-0.1.0.dev0.dist-info/METADATA
setty-0.1.0.dev0.dist-info/WHEEL
setty-0.1.0.dev0.dist-info/RECORD
