Metadata-Version: 2.1
Name: setty
Version: 0.1.0.dev0
Summary: A simple CLI tool for setting environment variables
Author: BiqRed
Author-email: biqred.shine@gmail.com
Requires-Python: >=3.8,<4.0
Classifier: Programming Language :: Python :: 3
Classifier: Programming Language :: Python :: 3.8
Classifier: Programming Language :: Python :: 3.9
Classifier: Programming Language :: Python :: 3.10
Classifier: Programming Language :: Python :: 3.11
Classifier: Programming Language :: Python :: 3.12
